sortgs/__init__.py
sortgs/sortgs.py
sortgs-1.0.7.dist-info/METADATA
sortgs-1.0.7.dist-info/WHEEL
sortgs-1.0.7.dist-info/entry_points.txt
sortgs-1.0.7.dist-info/top_level.txt
sortgs-1.0.7.dist-info/RECORD
