Metadata-Version: 2.1
Name: sortgs
Version: 1.0.7
Summary: A Python tool to rank Google Scholar publications by citations.
Author: Fernando Marcos Wittmann
Project-URL: github, https://github.com/WittmannF/sort-google-scholar
Classifier: Programming Language :: Python :: 3
Classifier: License :: OSI Approved :: MIT License
Classifier: Operating System :: OS Independent
Requires-Python: >=3.8
Requires-Dist: beautifulsoup4
Requires-Dist: matplotlib
Requires-Dist: pandas
Requires-Dist: requests
Requires-Dist: selenium
